Cargo.lock
Cargo.toml
MANIFEST.in
README.rst
glue.h
glue.pxd
glue.rs
htmlpyever.c
htmlpyever.pyx
setup.py
htmlpyever.egg-info/PKG-INFO
htmlpyever.egg-info/SOURCES.txt
htmlpyever.egg-info/dependency_links.txt
htmlpyever.egg-info/requires.txt
htmlpyever.egg-info/top_level.txt