Metadata-Version: 1.1
Name: htmlpyever
Version: 0.1.0.post2
Summary: Python bindings to html5ever
Home-page: https://github.com/tbodt/htmlpyever
Author: Theodore Dubois
Author-email: tblodt@icloud.com
License: LGPLv3
Keywords: html,html5,parser,parsing,html5ever
Platform: UNKNOWN
Classifier: Development Status :: 4 - Beta
Classifier: Intended Audience :: Developers
Classifier: License :: OSI Approved :: GNU Lesser General Public License v3 or later (LGPLv3+)
Classifier: Programming Language :: Python :: 3.5
Classifier: Topic :: Software Development :: Libraries :: Python Modules
Classifier: Topic :: Text Processing :: Markup :: HTML
